freekassa/__init__.py
freekassa/api.py
freekassa/api_base.py
freekassa/models/__init__.py
freekassa/models/balance.py
freekassa/type/__init__.py
freekassa/type/currencies.py
freekassa/type/languages.py
freekassa/type/order_statuses.py
freekassa/type/payment_methods.py
freekassa/utils.py
freekassa-0.1.4.dist-info/WHEEL
freekassa-0.1.4.dist-info/METADATA
freekassa-0.1.4.dist-info/RECORD
